pyriodic/Database.py
pyriodic/Structure.py
pyriodic/__init__.py
pyriodic/version.py
pyriodic/unit_cells/__init__.py
pyriodic_structures-0.2.1.dist-info/LICENSE
pyriodic_structures-0.2.1.dist-info/METADATA
pyriodic_structures-0.2.1.dist-info/WHEEL
pyriodic_structures-0.2.1.dist-info/entry_points.txt
pyriodic_structures-0.2.1.dist-info/top_level.txt
pyriodic_structures-0.2.1.dist-info/RECORD
