Metadata-Version: 2.1
Name: pyriodic-structures
Version: 0.2.1
Summary: Library to list and manipulate well-known 3D structures
Home-page: http://github.com/klarh/pyriodic-aflow
Author: Matthew Spellings
Author-email: matthew.p.spellings@gmail.com
License: MIT
Project-URL: Documentation, http://pyriodic.readthedocs.io/
Project-URL: Source, https://github.com/klarh/pyriodic
Platform: UNKNOWN
Classifier: Development Status :: 3 - Alpha
Classifier: License :: OSI Approved :: MIT License
Classifier: Programming Language :: Python :: 3
Requires-Python: >=3
Requires-Dist: numpy
